plangym/__init__.py
plangym/api_tests.py
plangym/core.py
plangym/environment_names.py
plangym/registry.py
plangym/utils.py
plangym/version.py
plangym/control/__init__.py
plangym/control/balloon.py
plangym/control/box_2d.py
plangym/control/classic_control.py
plangym/control/dm_control.py
plangym/control/lunar_lander.py
plangym/scripts/__init__.py
plangym/scripts/import_retro_roms.py
plangym/vectorization/__init__.py
plangym/vectorization/env.py
plangym/vectorization/parallel.py
plangym/vectorization/ray.py
plangym/videogames/__init__.py
plangym/videogames/atari.py
plangym/videogames/env.py
plangym/videogames/montezuma.py
plangym/videogames/nes.py
plangym/videogames/retro.py
plangym-0.1.30.dist-info/METADATA
plangym-0.1.30.dist-info/WHEEL
plangym-0.1.30.dist-info/licenses/LICENSE
plangym-0.1.30.dist-info/RECORD
