Metadata-Version: 2.4
Name: plangym
Version: 0.1.30
Summary: Plangym is an interface to use gymnasium for planning problems. It extends the standard interface to allow setting and recovering the environment states.
Author-email: Guillem Duran Ballester <guillem@fragile.tech>
Maintainer-email: Guillem Duran Ballester <guillem@fragile.tech>
License: MIT License
License-File: LICENSE
Keywords: RL,gymnasium,plangym,planning
Classifier: Development Status :: 3 - Alpha
Classifier: Intended Audience :: Developers
Classifier: License :: OSI Approved :: MIT License
Classifier: Programming Language :: Python :: 3.10
Classifier: Topic :: Software Development :: Libraries
Requires-Python: >=3.10
Requires-Dist: flogging>=0.0.22
Requires-Dist: fragile-gym
Requires-Dist: imageio>=2.35.1
Requires-Dist: numpy
Requires-Dist: opencv-python>=4.10.0.84
Requires-Dist: pillow; sys_platform != 'darwin'
Requires-Dist: pyglet==1.5.11
Requires-Dist: pyvirtualdisplay>=3.0
Provides-Extra: atari
Requires-Dist: ale-py; extra == 'atari'
Requires-Dist: gymnasium[accept-rom-license,atari]==0.*,>=0.29.1; extra == 'atari'
Provides-Extra: box-2d
Requires-Dist: box2d-py==2.3.5; extra == 'box-2d'
Provides-Extra: classic-control
Requires-Dist: gymnasium[classic-control]==0.*,>=0.29.1; extra == 'classic-control'
Requires-Dist: pygame>=2.6.0; extra == 'classic-control'
Provides-Extra: dm-control
Requires-Dist: dm-control>=1.0.22; extra == 'dm-control'
Requires-Dist: mujoco>=3.2.2; extra == 'dm-control'
Provides-Extra: docs
Requires-Dist: jupyter-cache; extra == 'docs'
Requires-Dist: linkify-it-py; extra == 'docs'
Requires-Dist: myst-nb; extra == 'docs'
Requires-Dist: myst-parser; extra == 'docs'
Requires-Dist: pydata-sphinx-theme; extra == 'docs'
Requires-Dist: ruyaml; extra == 'docs'
Requires-Dist: sphinx; extra == 'docs'
Requires-Dist: sphinx-autoapi; extra == 'docs'
Requires-Dist: sphinx-autodoc2; extra == 'docs'
Requires-Dist: sphinx-book-theme; extra == 'docs'
Requires-Dist: sphinx-copybutton; extra == 'docs'
Requires-Dist: sphinx-rtd-theme; extra == 'docs'
Requires-Dist: sphinx-togglebutton; extra == 'docs'
Requires-Dist: sphinxcontrib-bibtex; extra == 'docs'
Requires-Dist: sphinxcontrib-mermaid; extra == 'docs'
Requires-Dist: sphinxext-opengraph; extra == 'docs'
Provides-Extra: jupyter
Requires-Dist: jupyterlab>=3.2.0; extra == 'jupyter'
Provides-Extra: nes
Requires-Dist: fragile-gym-super-mario-bros>=7.4.1; extra == 'nes'
Requires-Dist: fragile-gym[accept-rom-license]; extra == 'nes'
Requires-Dist: fragile-nes-py>=10.0.1; extra == 'nes'
Provides-Extra: ray
Requires-Dist: ray>=2.35.0; extra == 'ray'
Provides-Extra: retro
Requires-Dist: stable-retro==0.9.1; (sys_platform == 'darwin') and extra == 'retro'
Requires-Dist: stable-retro==0.9.2; (sys_platform != 'darwin') and extra == 'retro'
Provides-Extra: test
Requires-Dist: hypothesis>=6.24.6; extra == 'test'
Requires-Dist: psutil>=5.8.0; extra == 'test'
Requires-Dist: pytest-cov>=3.0.0; extra == 'test'
Requires-Dist: pytest-rerunfailures>=10.2; extra == 'test'
Requires-Dist: pytest-xdist>=2.4.0; extra == 'test'
Requires-Dist: pytest>=6.2.5; extra == 'test'
Requires-Dist: pyvirtualdisplay>=1.3.2; extra == 'test'
Requires-Dist: tomli>=1.2.3; extra == 'test'
